.travis.yml
HISTORY.md
LICENSE
MANIFEST.in
README.md
TODO.md
setup.py
setup_long_description.rst
OpenRCV.egg-info/PKG-INFO
OpenRCV.egg-info/SOURCES.txt
OpenRCV.egg-info/dependency_links.txt
OpenRCV.egg-info/entry_points.txt
OpenRCV.egg-info/requires.txt
OpenRCV.egg-info/top_level.txt
data/sample.blt
docs/contributing.md
docs/releasing.md
openrcv/__init__.py
openrcv/counting.py
openrcv/main.py
openrcv/models.py
openrcv/parsing.py
openrcv/utils.py
openrcv/scripts/__init__.py
openrcv/scripts/main.py
openrcv/test/__init__.py
openrcv/test/test_parsing.py
openrcv/test/scripts/__init__.py
openrcv/test/scripts/test_main.py
openrcv_setup/__init__.py
openrcv_setup/pandoc.py
openrcv_setup/utils.py