Metadata-Version: 1.1
Name: OpenRCV
Version: 0.0.1-alpha
Summary: open-source software for tallying ranked-choice voting elections
Home-page: https://github.com/cjerdonek/open-rcv
Author: Chris Jerdonek
Author-email: chris.jerdonek@gmail.com
License: MIT
Keywords: ballot choice election ranked rcv single tally transferable stv vote voting
Platform: UNKNOWN
Classifier: Development Status :: 3 - Alpha
Classifier: Intended Audience :: Developers
Classifier: Topic :: Software Development :: Build Tools
Classifier: License :: OSI Approved :: MIT License
Classifier: Programming Language :: Python :: 3
Classifier: Programming Language :: Python :: 3.4
